{
    "description": "Element toggle",
    "origamiType": "module",
    "origamiVersion": 1,
    "support": "https://github.com/Pearson-Higher-Ed/o-collapse/issues",
    "supportStatus": "active",
    "browserFeatures": {
        "required": [
            "WeakMap",
            "createevent"
        ]
    },
    "demos": [
        {
            "path": "/demos/basic.html",
            "expanded": true,
            "description": ""
        },
        {
            "path": "/demos/accordion.html",
            "expanded": true,
            "description": ""
        }
    ]
}